bionemo/core/__init__.py
bionemo/core/api.py
bionemo/core/data/__init__.py
bionemo/core/data/api.py
bionemo/core/data/load.py
bionemo/core/data/multi_epoch_dataset.py
bionemo/core/data/permute.py
bionemo/core/data/resamplers.py
bionemo/core/data/resource.py
bionemo/core/data/resources/esm2.yaml
bionemo/core/data/resources/evo2.yaml
bionemo/core/data/resources/evo2_mamba.yaml
bionemo/core/data/resources/geneformer.yaml
bionemo/core/data/resources/scdl.yaml
bionemo/core/data/resources/single_cell.yaml
bionemo/core/model/__init__.py
bionemo/core/model/config.py
bionemo/core/utils/__init__.py
bionemo/core/utils/batching_utils.py
bionemo/core/utils/dtypes.py
bionemo/core/utils/random_utils.py
bionemo/core/utils/subprocess_utils.py
bionemo_core-2.4.5.dist-info/licenses/LICENSE
bionemo_core-2.4.5.dist-info/METADATA
bionemo_core-2.4.5.dist-info/WHEEL
bionemo_core-2.4.5.dist-info/entry_points.txt
bionemo_core-2.4.5.dist-info/top_level.txt
bionemo_core-2.4.5.dist-info/RECORD
