Metadata-Version: 2.4
Name: bionemo-core
Version: 2.4.5
Summary: BioNeMo core interfaces and PyTorch-related code.
Author-email: BioNeMo Team <bionemofeedback@nvidia.com>
License: 
Requires-Python: >=3.10
License-File: LICENSE
Requires-Dist: numpy
Requires-Dist: platformdirs
Requires-Dist: torch>=2.2.1
Requires-Dist: nest_asyncio
Requires-Dist: ngcsdk
Requires-Dist: pooch
Requires-Dist: pydantic[email]>=2.7.0
Requires-Dist: pyyaml
Requires-Dist: tqdm
Dynamic: license-file
